LICENSE.txt
MANIFEST.in
README.md
setup.py
sqliteanalyzer/__init__.py
sqliteanalyzer/header.py
sqliteanalyzer/manager.py
sqliteanalyzer/storageanalyzer.py
sqliteanalyzer/types.py
sqliteanalyzer.egg-info/PKG-INFO
sqliteanalyzer.egg-info/SOURCES.txt
sqliteanalyzer.egg-info/dependency_links.txt
sqliteanalyzer.egg-info/top_level.txt